setup.py
certbot_redis/__init__.py
certbot_redis/plugin.py
certbot_redis/redisurlparser.py
certbot_redis.egg-info/PKG-INFO
certbot_redis.egg-info/SOURCES.txt
certbot_redis.egg-info/dependency_links.txt
certbot_redis.egg-info/entry_points.txt
certbot_redis.egg-info/requires.txt
certbot_redis.egg-info/top_level.txt