Metadata-Version: 1.1
Name: certbot-redis
Version: 0.1.6
Summary: Certbot plugin for Redis
Home-page: https://github.com/deathowl/certbot-redis-plugin
Author: Balint Csergo
Author-email: <bcsergo@emarsys.com>
License: UNKNOWN
Keywords: certbot redis
Platform: UNKNOWN
Classifier: Development Status :: 4 - Beta
Classifier: Programming Language :: Python :: 2
Classifier: Programming Language :: Python :: 2.7
Classifier: Programming Language :: Python :: 3
Classifier: Programming Language :: Python :: 3.4
Classifier: Programming Language :: Python :: 3.5
Classifier: Programming Language :: Python :: 3.6
